MANIFEST.in
README.rst
setup.cfg
setup.py
collective/__init__.py
collective.pdfexport.egg-info/PKG-INFO
collective.pdfexport.egg-info/SOURCES.txt
collective.pdfexport.egg-info/dependency_links.txt
collective.pdfexport.egg-info/entry_points.txt
collective.pdfexport.egg-info/namespace_packages.txt
collective.pdfexport.egg-info/not-zip-safe
collective.pdfexport.egg-info/paster_plugins.txt
collective.pdfexport.egg-info/requires.txt
collective.pdfexport.egg-info/top_level.txt
collective/pdfexport/__init__.py
collective/pdfexport/adapter.py
collective/pdfexport/configure.zcml
collective/pdfexport/emailsource.py
collective/pdfexport/interfaces.py
collective/pdfexport/setuphandlers.py
collective/pdfexport/utility.py
collective/pdfexport/behavior/README.txt
collective/pdfexport/behavior/__init__.py
collective/pdfexport/behavior/configure.zcml
collective/pdfexport/browser/README.txt
collective/pdfexport/browser/__init__.py
collective/pdfexport/browser/download_pdf.py
collective/pdfexport/browser/send_as_pdf.py
collective/pdfexport/browser/templates/send_as_pdf.pt
collective/pdfexport/content/README.txt
collective/pdfexport/content/__init__.py
collective/pdfexport/locales/README.txt
collective/pdfexport/portlet/__init__.py
collective/pdfexport/portlet/configure.zcml
collective/pdfexport/profiles/default/browserlayer.xml
collective/pdfexport/profiles/default/collective.pdfexport.marker.txt
collective/pdfexport/profiles/default/cssregistry.xml
collective/pdfexport/profiles/default/jsregistry.xml
collective/pdfexport/profiles/default/metadata.xml
collective/pdfexport/profiles/default/portlets.xml
collective/pdfexport/profiles/default/types.xml
collective/pdfexport/schemaextender/__init__.py
collective/pdfexport/static/README.txt
collective/pdfexport/static/application-pdf.png
collective/pdfexport/static/mail.png
collective/pdfexport/upgrades/__init__.py
collective/pdfexport/upgrades/handlers.py
collective/pdfexport/upgrades/profiles.py
collective/pdfexport/viewlet/__init__.py
collective/pdfexport/viewlet/pdf_download.py
collective/pdfexport/viewlet/templates/pdf_download.pt
collective/pdfexport/vocabulary/__init__.py
docs/HISTORY.rst
docs/INSTALL.rst
docs/LICENSE.GPL
docs/LICENSE.txt